geo_db_sdk-1.0.0.dist-info/licenses/LICENSE
geodbcitiesapi/__init__.py
geodbcitiesapi/api_helper.py
geodbcitiesapi/configuration.py
geodbcitiesapi/geodbcitiesapi_client.py
geodbcitiesapi/controllers/__init__.py
geodbcitiesapi/controllers/base_controller.py
geodbcitiesapi/controllers/geo_controller.py
geodbcitiesapi/controllers/locale_controller.py
geodbcitiesapi/exceptions/__init__.py
geodbcitiesapi/exceptions/api_exception.py
geodbcitiesapi/exceptions/base_response_exception.py
geodbcitiesapi/http/__init__.py
geodbcitiesapi/http/http_call_back.py
geodbcitiesapi/http/http_method_enum.py
geodbcitiesapi/http/http_request.py
geodbcitiesapi/http/http_response.py
geodbcitiesapi/http/auth/__init__.py
geodbcitiesapi/http/auth/custom_header_authentication.py
geodbcitiesapi/models/__init__.py
geodbcitiesapi/models/base_collection_response.py
geodbcitiesapi/models/code_enum.py
geodbcitiesapi/models/countries_response.py
geodbcitiesapi/models/country_details.py
geodbcitiesapi/models/country_region_details.py
geodbcitiesapi/models/country_region_response.py
geodbcitiesapi/models/country_region_summary.py
geodbcitiesapi/models/country_regions_response.py
geodbcitiesapi/models/country_response.py
geodbcitiesapi/models/country_summary.py
geodbcitiesapi/models/currencies_response.py
geodbcitiesapi/models/currency.py
geodbcitiesapi/models/date_time_response.py
geodbcitiesapi/models/distance_response.py
geodbcitiesapi/models/error.py
geodbcitiesapi/models/error_code_enum.py
geodbcitiesapi/models/language.py
geodbcitiesapi/models/languages_response.py
geodbcitiesapi/models/link.py
geodbcitiesapi/models/locale.py
geodbcitiesapi/models/locales_response.py
geodbcitiesapi/models/metadata.py
geodbcitiesapi/models/populated_place_details.py
geodbcitiesapi/models/populated_place_response.py
geodbcitiesapi/models/populated_place_summary.py
geodbcitiesapi/models/populated_place_type_enum.py
geodbcitiesapi/models/populated_places_response.py
geodbcitiesapi/models/time_response.py
geodbcitiesapi/models/time_zone.py
geo_db_sdk-1.0.0.dist-info/METADATA
geo_db_sdk-1.0.0.dist-info/WHEEL
geo_db_sdk-1.0.0.dist-info/top_level.txt
geo_db_sdk-1.0.0.dist-info/RECORD
